odoo/addons/account_statement_import_online_qonto/README.rst
odoo/addons/account_statement_import_online_qonto/__init__.py
odoo/addons/account_statement_import_online_qonto/__manifest__.py
odoo/addons/account_statement_import_online_qonto/i18n/account_bank_statement_import_online_qonto.pot
odoo/addons/account_statement_import_online_qonto/i18n/account_statement_import_online_qonto.pot
odoo/addons/account_statement_import_online_qonto/i18n/it.po
odoo/addons/account_statement_import_online_qonto/models/__init__.py
odoo/addons/account_statement_import_online_qonto/models/online_bank_statement_provider_qonto.py
odoo/addons/account_statement_import_online_qonto/readme/CONFIGURE.rst
odoo/addons/account_statement_import_online_qonto/readme/CONTRIBUTORS.rst
odoo/addons/account_statement_import_online_qonto/readme/DESCRIPTION.rst
odoo/addons/account_statement_import_online_qonto/readme/USAGE.rst
odoo/addons/account_statement_import_online_qonto/static/description/icon.png
odoo/addons/account_statement_import_online_qonto/static/description/index.html
odoo/addons/account_statement_import_online_qonto/tests/__init__.py
odoo/addons/account_statement_import_online_qonto/tests/test_account_statement_import_online_qonto.py
odoo/addons/account_statement_import_online_qonto/view/online_bank_statement_provider.xml
odoo_addon_account_statement_import_online_qonto-16.0.1.0.1.dist-info/METADATA
odoo_addon_account_statement_import_online_qonto-16.0.1.0.1.dist-info/WHEEL
odoo_addon_account_statement_import_online_qonto-16.0.1.0.1.dist-info/top_level.txt
odoo_addon_account_statement_import_online_qonto-16.0.1.0.1.dist-info/RECORD
