Metadata-Version: 2.1
Name: odoo-addon-account_statement_import_online_qonto
Version: 16.0.1.0.1
Summary: Online Bank Statements: Qonto
Home-page: https://github.com/OCA/bank-statement-import
Author: Florent de Labarre, Odoo Community Association (OCA)
Author-email: support@odoo-community.org
License: AGPL-3
Classifier: Programming Language :: Python
Classifier: Framework :: Odoo
Classifier: Framework :: Odoo :: 16.0
Classifier: License :: OSI Approved :: GNU Affero General Public License v3
Requires-Python: >=3.10
Requires-Dist: odoo-addon-account-statement-import-online <16.1dev,>=16.0dev
Requires-Dist: odoo <16.1dev,>=16.0a
